autoxkit/__init__.py
autoxkit/icmatch/__init__.py
autoxkit/icmatch/color_matcher.py
autoxkit/icmatch/image_matcher.py
autoxkit/icmatch/tools.py
autoxkit/mousekey/__init__.py
autoxkit/mousekey/constants.py
autoxkit/mousekey/hook_listener.py
autoxkit/mousekey/hotkey_listener.py
autoxkit/mousekey/keyboard.py
autoxkit/mousekey/mouse.py
autoxkit-0.4.3.dist-info/licenses/LICENSE.txt
autoxkit-0.4.3.dist-info/METADATA
autoxkit-0.4.3.dist-info/WHEEL
autoxkit-0.4.3.dist-info/top_level.txt
autoxkit-0.4.3.dist-info/RECORD
