Metadata-Version: 2.4
Name: autoxkit
Version: 0.4.3
Summary: Python library for automating Windows
Author-email: YorickFin <1582456060@qq.com>
License: GPL-3.0-or-later
Project-URL: Homepage, https://github.com/YorickFin/autoxkit
Classifier: License :: OSI Approved :: GNU General Public License v3 (GPLv3)
Classifier: Operating System :: Microsoft :: Windows
Classifier: Programming Language :: Python :: 3
Classifier: Programming Language :: Python :: 3.10
Classifier: Programming Language :: Python :: 3.11
Classifier: Programming Language :: Python :: 3.12
Classifier: Programming Language :: Python :: 3.13
Requires-Python: >=3.10
License-File: LICENSE.txt
Requires-Dist: mss>=7.0.1
Requires-Dist: numpy>=1.19.5
Requires-Dist: scipy>=1.5.4
Dynamic: license-file
